{
  "slug": "brand-ar",
  "name": "Brand AR",
  "liveLink": "https://nv25.ffind.com/nv_rev2/login.php",
  "testLink": "https://nv25.ffind.com/nv_rev2/test.php?token=wIK0ca8Oe9",
  "mode": "Freestyle",
  "loiTargetMinutes": 15,
  "loiJitterPercent": 15,
  "maxWorkers": 2,
  "savFieldMap": {
    "station": "ws",
    "password": "password",
    "id": "s_ini",
    "project": "project"
  },
  "exploreSeedRowIndex": 0,
  "exploreRowCount": 1,
  "exploreEndQuestions": [
    "ANMER"
  ],
  "activeDatasetId": "47cfb062",
  "createdAt": "2026-06-26T12:24:14.203Z",
  "updatedAt": "2026-06-26T12:32:58.764Z"
}
